pytest_thawgun/__init__.py
pytest_thawgun/plugin.py
pytest_thawgun-0.0.3.dist-info/LICENSE
pytest_thawgun-0.0.3.dist-info/METADATA
pytest_thawgun-0.0.3.dist-info/WHEEL
pytest_thawgun-0.0.3.dist-info/entry_points.txt
pytest_thawgun-0.0.3.dist-info/top_level.txt
pytest_thawgun-0.0.3.dist-info/RECORD
